{
  "title": "AWS re:Invent 2025 - Modernizing Global Payment Processing: Moving from Mainframe to AWS (SPS312)",
  "title_cn": "AWS re:Invent 2025 - 现代化全球支付处理：从大型机迁移到AWS (SPS312)",
  "abstract": "Learn how Global Payments is transforming its 40-year-old mainframe system into a modern AWS cloud platform. This major financial services company, which processes credit cards for over 600 million cardholders worldwide, is using enhanced support and monitoring tools to ensure a reliable transition to cloud-based processing.",
  "abstract_cn": "了解Global Payments如何将其拥有40年历史的大型机系统转型为现代化的AWS云平台。这家大型金融服务公司为全球超过6亿持卡人处理信用卡业务，正在使用增强的支持和监控工具来确保可靠地过渡到基于云的处理系统。",
  "presenter": [
    {
      "name": "Stephen Clarke",
      "title": "Director",
      "company": "Amazon Web Services"
    },
    {
      "name": "Ganesh Somaskandan",
      "title": "Vice President",
      "company": "Global Payments"
    }
  ],
  "attributes": {
    "topic": "Migration & Modernization",
    "area_of_interest": [
      "Resilience"
    ],
    "services": [],
    "type": "Breakout session"
  },
  "video_url": "https://www.youtube.com/watch?v=rU3ACmPoeaQ",
  "session_code": "SPS312"
}