{
  "title": "AWS re:Invent 2025 - Unifying AWS observability, logs, and traces with Dynatrace (AIM210)",
  "title_cn": "AWS re:Invent 2025 - 使用 Dynatrace 统一 AWS 可观测性、日志和追踪 (AIM210)",
  "abstract": "Learn how Dynatrace Grail® and Davis® AI provide a unified approach to logs, metrics, and traces across Amazon Web Services. Eliminate monitoring silos, gain real-time insights, and speed up root-cause analysis with expert strategies for streamlined observability and enhanced AWS operations. This presentation is brought to you by Dynatrace, an AWS Partner.",
  "abstract_cn": "了解 Dynatrace Grail® 和 Davis® AI 如何为 Amazon Web Services 提供统一的日志、指标和追踪方法。通过专家策略消除监控孤岛，获得实时洞察，加快根因分析，实现简化的可观测性并增强 AWS 运营。本演示由 AWS 合作伙伴 Dynatrace 提供。",
  "presenter": [
    {
      "name": "Frank Schwarzenau",
      "title": "WW Observability Partner Lead",
      "company": "AWS"
    },
    {
      "name": "Alex Hibbitt",
      "title": "Enginnering Director, Customer Platform",
      "company": "Storio Group"
    },
    {
      "name": "Jason Ostroski",
      "title": "Field CTO",
      "company": "Dynatrace"
    }
  ],
  "attributes": {
    "topic": "Migration & Modernization",
    "area_of_interest": [
      "Generative AI",
      "Monitoring & Observability",
      "Open Data"
    ],
    "services": [
      "Amazon Data Firehose",
      "Amazon Elastic Compute Cloud (Amazon EC2)",
      "Amazon Simple Storage Service (Amazon S3)"
    ],
    "type": "Breakout session"
  },
  "video_url": "https://www.youtube.com/watch?v=j-jo1-n9S8E",
  "session_code": "AIM210-S"
}