{
  "title": "AWS re:Invent 2025 - Protect your data with AWS Backup: overview, use cases and what's new (STG207)",
  "title_cn": "AWS re:Invent 2025 - 使用 AWS Backup 保护您的数据：概述、使用案例和新功能 (STG207)",
  "abstract": "AWS Backup helps over 140,000 customers protect more than 2.9 exabytes of application data across AWS services. It offers policy-based data protection, streamlining backup management, enhancing security controls, and simplifying compliance reporting. In this session, you'll learn how to use AWS Backup, hear what's new, and discover practical implementation strategies. Plus, hear directly from customers about their real-world experiences using AWS Backup to protect mission-critical workloads and maintain business continuity. Whether you're new to AWS Backup or a seasoned user, this session will provide valuable insights into protecting your AWS environment.",
  "abstract_cn": "AWS Backup 帮助超过 140,000 名客户保护跨 AWS 服务的超过 2.9 艾字节的应用程序数据。它提供基于策略的数据保护，简化备份管理，增强安全控制，并简化合规性报告。在本次会议中，您将学习如何使用 AWS Backup，了解最新功能，并发现实用的实施策略。此外，您还将直接听取客户关于使用 AWS Backup 保护关键任务工作负载和维护业务连续性的实际经验。无论您是 AWS Backup 的新用户还是经验丰富的用户，本次会议都将为保护您的 AWS 环境提供宝贵的见解。",
  "presenter": [
    {
      "name": "Palak Desai",
      "title": "Sr. Manager, Product",
      "company": "Amazon"
    },
    {
      "name": "Bisman Sethi",
      "title": "Sr Product Manager",
      "company": "Amazon"
    },
    {
      "name": "Rooshir Patel",
      "title": "Managing Director, General Manager - Data Protection & Recovery Product Line",
      "company": "JPMorgan Chase"
    },
    {
      "name": "Chuck Uwanna",
      "title": "Principal Application Architect - Strategy and Modernization",
      "company": "Exxonmobil"
    }
  ],
  "attributes": {
    "topic": "Storage",
    "area_of_interest": [
      "Data Protection",
      "Disaster Response & Recovery",
      "Resilience"
    ],
    "services": [
      "AWS Backup"
    ],
    "type": "Breakout session"
  },
  "video_url": "https://www.youtube.com/watch?v=6v8NfD9rqRE",
  "session_code": "STG207"
}