{
  "title": "AWS re:Invent 2025 - Implementing security best practices for serverless applications (CNS360)",
  "title_cn": "AWS re:Invent 2025 - 为无服务器应用程序实施安全最佳实践 (CNS360)",
  "abstract": "Discover how to maximize security in serverless architectures while maintaining developer velocity. This session explores enterprise-proven security best practices across the serverless application lifecycle, from development to production. Learn how to leverage AWS's built-in security features, implement effective security controls, and establish proper guardrails without hampering innovation. Drawing from real customer experiences, we'll demonstrate practical approaches to strengthen your security posture while enabling developers to build and deploy with confidence",
  "abstract_cn": "了解如何在无服务器架构中最大化安全性，同时保持开发人员的工作效率。本次会议探讨了经过企业验证的安全最佳实践，涵盖从开发到生产的无服务器应用程序生命周期。学习如何利用 AWS 的内置安全功能、实施有效的安全控制，以及建立适当的防护措施而不妨碍创新。我们将借鉴真实客户经验，展示实用方法来增强您的安全态势，同时使开发人员能够自信地构建和部署应用程序。",
  "presenter": [
    {
      "name": "Chris McPeek",
      "title": "WW Tech Lead - Serverless",
      "company": "AWS"
    },
    {
      "name": "Heeki Park",
      "title": "Principal Solutions Architect",
      "company": "AWS"
    }
  ],
  "attributes": {
    "topic": "Serverless & Containers",
    "area_of_interest": [
      "Application Security",
      "Lambda-Based Applications",
      "Serverless"
    ],
    "services": [
      "Amazon API Gateway",
      "AWS Lambda",
      "AWS Step Functions"
    ],
    "type": "Breakout session"
  },
  "video_url": "https://www.youtube.com/watch?v=yDhR5VwcnYo",
  "session_code": "CNS360"
}