{
  "title": "AWS re:Invent 2025 - Integration patterns for distributed systems (API315)",
  "title_cn": "AWS re:Invent 2025 - 分布式系统的集成模式 (API315)",
  "abstract": "Today's applications are interconnected: they expose APIs, publish events, call third-party services, and externalize states. They must therefore address the fundamental challenges of distributed systems, such as out-of-order delivery, retries, idempotence, and partial failures. To address these challenges, architects must carefully evaluate integration options while considering how to manage complex system interactions. In this session, learn about common design trade-offs for distributed systems and how to navigate them with design patterns, illustrated by examples.",
  "abstract_cn": "当今的应用程序是相互连接的：它们公开API、发布事件、调用第三方服务并外部化状态。因此，它们必须解决分布式系统的基本挑战，例如乱序交付、重试、幂等性和部分故障。为了应对这些挑战，架构师必须仔细评估集成选项，同时考虑如何管理复杂的系统交互。在本次会议中，了解分布式系统的常见设计权衡以及如何通过设计模式来应对这些权衡，并通过示例进行说明。",
  "presenter": [
    {
      "name": "Dirk Froehner",
      "title": "Principal Solutions Architect",
      "company": "Amazon Web Services"
    },
    {
      "name": "Maximilian Schellhorn",
      "title": "Senior Solutions Architect",
      "company": "AWS"
    }
  ],
  "attributes": {
    "topic": "Application Integration",
    "area_of_interest": [
      "Event-Driven Architecture",
      "Serverless"
    ],
    "services": [
      "Amazon EventBridge",
      "Amazon Simple Notification Service (Amazon SNS)",
      "Amazon Simple Queue Service (Amazon SQS)"
    ],
    "type": "Breakout session"
  },
  "video_url": "https://www.youtube.com/watch?v=xc9P6wbhLwE",
  "session_code": "API315"
}