{
  "title": "AWS re:Invent 2025 - Observability for Reliable Agentic AI with Strands SDK & OpenTelemetry (NTA406)",
  "title_cn": "AWS re:Invent 2025 - 使用 Strands SDK 和 OpenTelemetry 实现可靠的智能体 AI 可观测性 (NTA406)",
  "abstract": "Reliable agentic AI requires robust observability. In this hands-on session, learn how to instrument and monitor AI systems using OpenTelemetry with AWS native tools and open-source solutions. Explore real-world implementations using Strands SDK, diagnostic methodologies for typical use cases, and strategies for continuous improvement. Join us for a gamified experience troubleshooting an agentic application, and leave with practical skills to implement observability at scale.",
  "abstract_cn": "可靠的智能体 AI 需要强大的可观测性。在本动手实践课程中，学习如何使用 OpenTelemetry 结合 AWS 原生工具和开源解决方案来检测和监控 AI 系统。探索使用 Strands SDK 的实际实现、典型用例的诊断方法以及持续改进策略。加入我们的游戏化体验，对智能体应用程序进行故障排除，并掌握大规模实施可观测性的实用技能。",
  "presenter": [
    {
      "name": "Gabriel Paredes",
      "title": "Sr. Solutions Architect",
      "company": "AWS"
    },
    {
      "name": "Luis Eduardo Torres",
      "title": "Solutions Architecture Manager",
      "company": "Amazon Web Services"
    }
  ],
  "attributes": {
    "topic": "Cloud Operations",
    "area_of_interest": [
      "Generative AI",
      "Agentic AI"
    ],
    "services": [
      "Amazon Bedrock",
      "Amazon CloudWatch"
    ],
    "type": "Code talk"
  },
  "video_url": "https://www.youtube.com/watch?v=qJxF4XfMLhk",
  "session_code": "NTA406"
}