{
  "title": "AWS re:Invent 2025 - Transforming Apache Kafka into a Scalable Message Queue (OPN413)",
  "title_cn": "AWS re:Invent 2025 - 将 Apache Kafka 转变为可扩展的消息队列 (OPN413)",
  "abstract": "Event streaming in Apache Kafka is powerful, but sometimes a queue-based model is more suited for workloads where parallel consumption is more important than ordering. KIP-932 introduces share groups, a feature that allows consumers to cooperatively consume data from Kafka topics, akin to how message queues work. This enables per-message acknowledgment, retries, and load distribution without the complexities of partition management. Ideal for independent work items, this approach simplifies message handling and enhances scalability. Join us to learn how KIP-932 brings queuing semantics to Kafka, enabling more flexible, efficient processing in event-driven architectures.",
  "abstract_cn": "Apache Kafka 中的事件流处理功能强大，但有时基于队列的模型更适合并行消费比顺序更重要的工作负载。KIP-932 引入了共享组功能，允许消费者协作地从 Kafka 主题消费数据，类似于消息队列的工作方式。这实现了按消息确认、重试和负载分配，而无需处理分区管理的复杂性。这种方法非常适合独立的工作项，简化了消息处理并增强了可扩展性。加入我们，了解 KIP-932 如何将队列语义引入 Kafka，在事件驱动架构中实现更灵活、高效的处理。",
  "presenter": [
    {
      "name": "Subham Rakshit",
      "title": "Sr. Streaming SA",
      "company": "Amazon Web Services"
    },
    {
      "name": "Masudur Rahaman Sayem",
      "title": "Sr. WW SSA Streaming",
      "company": "AWS"
    }
  ],
  "attributes": {
    "topic": "Open Source",
    "area_of_interest": [
      "Event-Driven Architecture"
    ],
    "services": [],
    "type": "Breakout session"
  },
  "video_url": "https://www.youtube.com/watch?v=zbN1VeenxY4",
  "session_code": "OPN413"
}