{
  "title": "AWS re:Invent 2025 - Debug Lambda functions deployed in cloud like never before (CNS367)",
  "title_cn": "AWS re:Invent 2025 - 以前所未有的方式调试部署在云端的 Lambda 函数 (CNS367)",
  "abstract": "Discover AWS Lambda's groundbreaking remote debugging capability, allowing developers to debug functions deployed in AWS cloud from local IDE for the first time. Learn how to set breakpoints, step through code line-by-line, inspect variables, and analyze call stacks in live Lambda functions. Experience practical debugging techniques for complex serverless scenarios with minimal setup and performance impact. Whether you're new to Lambda or an experienced developer, this session will transform your debugging workflow, dramatically reducing troubleshooting time and improving development efficiency.",
  "abstract_cn": "探索 AWS Lambda 突破性的远程调试功能,让开发者首次能够从本地 IDE 调试部署在 AWS 云中的函数。学习如何在实时 Lambda 函数中设置断点、逐行单步执行代码、检查变量和分析调用堆栈。体验针对复杂无服务器场景的实用调试技术,只需最少的设置且对性能影响极小。无论您是 Lambda 新手还是经验丰富的开发者,本次会议都将改变您的调试工作流程,大幅缩短故障排除时间并提高开发效率。",
  "presenter": [
    {
      "name": "Shridhar Pandey",
      "title": "Principal Product Manager",
      "company": "AWS"
    },
    {
      "name": "Harold Sun",
      "title": "Senior Software Development Engineer",
      "company": "Amazon Web Services"
    }
  ],
  "attributes": {
    "topic": "Serverless & Containers",
    "area_of_interest": [
      "Lambda-Based Applications",
      "Serverless"
    ],
    "services": [
      "AWS Lambda"
    ],
    "type": "Breakout session"
  },
  "video_url": "https://www.youtube.com/watch?v=yFmaMNN75-c",
  "session_code": "CNS367"
}